pyleetx/__init__.py
pyleetx/leetx.py
pyleetx-0.1.0.dist-info/METADATA
pyleetx-0.1.0.dist-info/WHEEL
pyleetx-0.1.0.dist-info/top_level.txt
pyleetx-0.1.0.dist-info/RECORD
