Metadata-Version: 2.1
Name: pyleetx
Version: 0.1.0
Summary: Python interface to 1337x.to
Home-page: https://github.com/srob650/pyleetx
Author: srob650
Author-email: pytvmaze@gmail.com
License: MIT
Keywords: python leetx 1337x torrents torrent
Platform: UNKNOWN
Classifier: Development Status :: 2 - Pre-Alpha
Classifier: Intended Audience :: Developers
Classifier: License :: OSI Approved :: MIT License
Classifier: Programming Language :: Python :: 2.7
Classifier: Programming Language :: Python :: 3.5
Requires-Dist: requests
Requires-Dist: beautifulsoup4
